plotsettings/__init__.py
plotsettings/__init__.pyc
plotsettings/journals.py
plotsettings/journals.pyc
plotsettings/set.py
plotsettings/set.pyc
plotsettings/test/__init__.py
plotsettings/test/__init__.pyc
plotsettings/test/custom_journals.py
plotsettings/test/custom_journals.pyc
plotsettings/test/test_labelling.py
plotsettings/test/__pycache__/test_labelling.cpython-27-PYTEST.pyc
plotsettings-1.0.4_2.dist-info/DESCRIPTION.rst
plotsettings-1.0.4_2.dist-info/METADATA
plotsettings-1.0.4_2.dist-info/metadata.json
plotsettings-1.0.4_2.dist-info/RECORD
plotsettings-1.0.4_2.dist-info/top_level.txt
plotsettings-1.0.4_2.dist-info/WHEEL
