Metadata-Version: 2.0
Name: plotsettings
Version: 1.0.4-2
Summary: Easily format figures to match the publication requirements of an academic journal
Home-page: UNKNOWN
Author: Gen Del Raye
Author-email: gdelraye@hawaii.edu
License: UNKNOWN
Keywords: matplotlib,rcParams,journal,figure size,plot settings,panel labels
Platform: UNKNOWN
Classifier: Intended Audience :: Science/Research
Classifier: License :: OSI Approved :: GNU General Public License v3 (GPLv3)
Classifier: Natural Language :: English
Classifier: Operating System :: OS Independent
Classifier: Programming Language :: Python
Classifier: Topic :: Scientific/Engineering
Classifier: Development Status :: 4 - Beta
